graphworks/__init__.py
graphworks/edge.py
graphworks/graph.py
graphworks/algorithms/__init__.py
graphworks/algorithms/basic.py
graphworks/algorithms/directed.py
graphworks/algorithms/search.py
graphworks/algorithms/sort.py
graphworks/export/__init__.py
graphworks/export/graphviz_utils.py
graphworks/export/json_utils.py
graphworks-0.5.0.dist-info/LICENSE
graphworks-0.5.0.dist-info/METADATA
graphworks-0.5.0.dist-info/WHEEL
graphworks-0.5.0.dist-info/top_level.txt
graphworks-0.5.0.dist-info/RECORD
