Metadata-Version: 2.1
Name: graphworks
Version: 0.5.0
Summary: Graph theoretic classes and helper functions.
Home-page: https://github.com/nathan-gilbert/graphworks
Author: Nathan Gilbert
Author-email: nathan.gilbert@gmail.com
License: MIT
Project-URL: Bug Tracker, https://github.com/nathan-gilbert/graphworks/issues
Classifier: Intended Audience :: Developers
Classifier: Intended Audience :: Education
Classifier: Intended Audience :: Science/Research
Classifier: Programming Language :: Python
Classifier: Programming Language :: Python :: 3
Classifier: Programming Language :: Python :: 3.7
Classifier: Programming Language :: Python :: 3.8
Classifier: Programming Language :: Python :: 3.9
Classifier: Operating System :: OS Independent
Classifier: Topic :: Scientific/Engineering :: Mathematics
Requires-Python: >=3.7
License-File: LICENSE
Requires-Dist: numpy (==1.21.5)
Requires-Dist: graphviz (==0.19.1)
